setup.py
dynamic_threadlocal/__init__.py
dynamic_threadlocal.egg-info/PKG-INFO
dynamic_threadlocal.egg-info/SOURCES.txt
dynamic_threadlocal.egg-info/dependency_links.txt
dynamic_threadlocal.egg-info/entry_points.txt
dynamic_threadlocal.egg-info/top_level.txt
dynamic_threadlocal.egg-info/zip-safe