Metadata-Version: 1.0
Name: dynamic-threadlocal
Version: 0.1
Summary: Dynamic scoping using thread-local scoping
Home-page: UNKNOWN
Author: Jonathan Gardner
Author-email: jgardner@jonathangardner.net
License: GPL
Platform: UNKNOWN
